{
  "generated_at": "2026-05-02T03:46:18Z",
  "cutoff_utc": "2026-05-01T03:46:18Z",
  "mode": "fallback_recent",
  "count": 3,
  "posts": [
    {
      "id": "647110288496461_122179856018942538",
      "message": "🚨 FREEZER CLEAN OUT SALE – THIS WEEKEND ONLY! 🚨\n\n🔔YOU GUYS ARE AMAZING! TRULY! \nWe are sold out of freezer thighs and whole legs! We do have 2 orders of drumsticks left! \nWe do have fresh whole legs available if interested! \n\nHelp us make room for the next batch!\n🥩 10 lbs MIX & MATCH, you choose the cuts! \n• Thighs\n• Drumsticks\n• Whole legs\n💥 ONLY $25 💥\n\nThe first 10 orders gets a special added surprise from us! \n\nPerfect for grilling, meal prep, or stocking up!\n📩 Message us to claim yours before they’re gone — limited availability!",
      "created_time": "2026-05-01T14:24:39+0000",
      "permalink_url": "https://www.facebook.com/122162141804942538/posts/122179856018942538",
      "full_picture": "https://scontent-ord5-1.xx.fbcdn.net/v/t39.30808-6/688009771_122179855970942538_1820611475800531482_n.jpg?stp=cp1_dst-jpg_p720x720_tt6&_nc_cat=101&ccb=1-7&_nc_sid=7b2446&_nc_ohc=KNsdN8FzsN4Q7kNvwGrloyh&_nc_oc=Adr0bMGZSYRh83VJQHBYTCbqmoopnF00iiQ5oUu8-NYn3N_1IeoHNQwT3wTngiPr60o&_nc_zt=23&_nc_ht=scontent-ord5-1.xx&edm=AKK4YLsEAAAA&_nc_gid=l0UZ81CuwC2q5bT_AZyDaA&_nc_tpa=Q5bMBQHWDkaCZvNyeLTA1Wmb5ViWZQt_tx9jwV_qvTqOxyPQ2_WYQTmHbcyWGGPqaTjR9nVTBDDETm_ZBQ&oh=00_Af6TxsQEjllYdHa19Ha2PqpovOMetL-xuGY79VVsivvDkA&oe=69FB55BE"
    },
    {
      "id": "647110288496461_122179254920942538",
      "message": "🐷✨ Piglet Time on the Farm! ✨🐷\nThe wait is over… our piglets have arrived and we are already obsessed! These little ones are full of personality, zoomies, and the cutest snorts you’ve ever heard.\nFrom wobbly first steps to curious little noses exploring everything, there’s never a dull moment around here right now. 💕\nStay tuned for more photos and updates as they grow — trust us, you won’t want to miss it!\n#PigletTime #FarmLife #RoswellFamilyFarm #BabyAnimals #SpringOnTheFarm",
      "created_time": "2026-04-28T18:33:08+0000",
      "permalink_url": "https://www.facebook.com/122162141804942538/posts/122179254920942538",
      "full_picture": "https://scontent-ord5-1.xx.fbcdn.net/v/t39.30808-6/682408534_122179254896942538_8129833721788711881_n.jpg?stp=cp1_dst-jpg_p720x720_tt6&_nc_cat=101&ccb=1-7&_nc_sid=7b2446&_nc_ohc=XRoAHIY4AmQQ7kNvwEN0EgK&_nc_oc=AdrnnLlNqkStt2dWpuB7B5EGs8qvLiX_iqzay12bryQL_LDuAwL6DOga2-8NXrug8jg&_nc_zt=23&_nc_ht=scontent-ord5-1.xx&edm=AKK4YLsEAAAA&_nc_gid=l0UZ81CuwC2q5bT_AZyDaA&_nc_tpa=Q5bMBQFrqlTorjgdyyDimBtE0uXZH4aqt9pkGau6sRU80GjwlyzUczL6677ZRHsy9CgRK4pgLsbIV9x3PQ&oh=00_Af6WoLsHHX5SbdH4kIZtsvyiRTGfd9DmgA6ABhL5rpaiyA&oe=69FB3458"
    },
    {
      "id": "647110288496461_122178781556942538",
      "message": "Don’t forget, EGG DEAL TODAY! \nUntil sold out! 🙂\n\nThank you so much for supporting our local farm 🌾",
      "created_time": "2026-04-26T13:04:26+0000",
      "permalink_url": "https://www.facebook.com/122162141804942538/posts/122178781556942538",
      "full_picture": "https://scontent-ord5-3.xx.fbcdn.net/v/t39.30808-6/683389028_122178781502942538_3812781603431964654_n.jpg?stp=dst-jpg_p720x720_tt6&_nc_cat=106&ccb=1-7&_nc_sid=7b2446&_nc_ohc=VjMJR4Nv_G8Q7kNvwFXtogV&_nc_oc=AdqopgL_jwmc_YnOb6Wg2P_2kdZRkUEXtNL5vqlux2jy8egGBDXKOwoiEEpinUOTWG4&_nc_zt=23&_nc_ht=scontent-ord5-3.xx&edm=AKK4YLsEAAAA&_nc_gid=l0UZ81CuwC2q5bT_AZyDaA&_nc_tpa=Q5bMBQHpb3z42Y97-mrGkaQgDwxLWyUjeM-2yi4MIKmuTmPEqF8Vriwt16s9LwuooNwqSpztdG-o2fW3CA&oh=00_Af4FEfpbpn4TSFQzraYGlWooDEAfEy55q-EEYMBpKZlqlg&oe=69FB4FB9"
    }
  ]
}