{
  "generated_at": "2026-05-30T14:01:26Z",
  "cutoff_utc": "2026-05-29T14:01:26Z",
  "mode": "fallback_recent",
  "count": 3,
  "posts": [
    {
      "id": "647110288496461_122184521540942538",
      "message": "🌿🐓 STOCK THE FREEZER WITH FARM-FRESH CHICKEN 🐓🌿\nFrom our family farm to your dinner table — pasture-raised chicken available now at Roswell Family Farm!\n✨ Current Cuts Available:\n• Chicken Breast — $6.90/lb\n• Thighs — $4.25/lb\n• Drumsticks — $3.50/lb\n• Whole Chickens — $3.90/lb\nPerfect for grilling, meal prep, soups, or stocking the freezer! We only have a few whole chickens available, so grab them while they last. 🐔\nMessage us to order or reserve yours today!\n📍 Roswell Family Farm\n#RoswellFamilyFarm #FarmFreshChicken #PastureRaised #ShopLocal #FreezerFill #FarmToTable",
      "created_time": "2026-05-24T18:39:29+0000",
      "permalink_url": "https://www.facebook.com/122162141804942538/posts/122184521540942538",
      "full_picture": null
    },
    {
      "id": "647110288496461_122184312356942538",
      "message": "🚜Meet us at the Farmers Market! 🐓🐖\n📌Dolgeville - Plowe Park \n⏰9-1! \n\nCome and see us! 😍\n\nPeep the duckling Willow wants to bring home! 🥰",
      "created_time": "2026-05-23T13:22:03+0000",
      "permalink_url": "https://www.facebook.com/122162141804942538/posts/122184312356942538",
      "full_picture": "https://scontent-iad3-1.xx.fbcdn.net/v/t39.30808-6/704751190_122184312332942538_8318576259574034321_n.jpg?stp=cp1_dst-jpg_s960x960_tt6&_nc_cat=110&ccb=1-7&_nc_sid=833d8c&_nc_ohc=ChPbIeN9tTcQ7kNvwFD0K0h&_nc_oc=Adp1NyR5pUeSV-px9SlU4xiabJrJswGuXFto8HJQJ1jme1ME-JcCXEv_3Wa6W5KEYX0&_nc_zt=23&_nc_ht=scontent-iad3-1.xx&edm=AKK4YLsEAAAA&_nc_gid=dYLSZD8ewwh4thGlamuRlA&_nc_tpa=Q5bMBQFTC5DnQxurdAABDPcYGzFw00wRR9e21oRgsqZsfucWGsi_j_EfNX4Z6LCQz8YLhTULqLR4dQe_kA&oh=00_Af6cclGN7o_SsBw98mywLtPk1Qbo1TSjII3NT2lJGoB1bA&oe=6A20A9B8"
    },
    {
      "id": "647110288496461_122183905412942538",
      "message": "Did Memorial Day weekend creep up on anyone else?? 🤪\nHaven’t even planned what to eat this weekend?\nWe’ve got you covered! 🍗\nChicken leg quarters, thighs, drumsticks — we’ve got it all! 🙂\nPlus PORK CUTS! 🥓\nWe’ll be at the Dolgeville Farmers Market this Saturday from 9–1!\nIf you’d like anything special, send us a message to reserve your order for market pick-up!",
      "created_time": "2026-05-22T00:15:39+0000",
      "permalink_url": "https://www.facebook.com/122162141804942538/posts/122183905412942538",
      "full_picture": "https://scontent-iad6-1.xx.fbcdn.net/v/t39.30808-6/702696619_122183905388942538_9184088811190483685_n.jpg?stp=dst-jpg_p720x720_tt6&_nc_cat=100&ccb=1-7&_nc_sid=833d8c&_nc_ohc=_1N38fINsw8Q7kNvwFHoCDc&_nc_oc=AdqxSF3v1BrPrc7uS5O8U6s5ubGWvYIOznr_RfyzaG0np1jw3nUbbi6aCV6ZGPHDlC4&_nc_zt=23&_nc_ht=scontent-iad6-1.xx&edm=AKK4YLsEAAAA&_nc_gid=dYLSZD8ewwh4thGlamuRlA&_nc_tpa=Q5bMBQGCwDxL0gVzvXEg2rQH3BUIK3dIouX_hYJYSIG8tAdXGKlTJC1_6aso7Cr69Um5K5Guwaa3hDvv-g&oh=00_Af4A9wuTNhkXdn11aM3LNRphC0sNJ5pvNf_F4CyTjv_CQA&oe=6A20B06D"
    }
  ]
}