{
  "generated_at": "2026-03-20T05:07:32Z",
  "cutoff_utc": "2026-03-19T05:07:32Z",
  "mode": "fallback_recent",
  "count": 3,
  "posts": [
    {
      "id": "647110288496461_122171355008942538",
      "message": "🐥 The kids have been BUSY this week… 🐥\nWe welcomed 200 new baby chicks to the farm this past weekend!! 😍\nLet’s just say…\nThere’s been a lot of excitement, a little chaos, and a whole lot of peeping going on 🐣😂\nThe kids are already hard at work helping care for them—making sure they’re warm, fed, and getting plenty of love ❤️\nThis is what it’s all about for us…\nRaising food, raising kids, and raising them to know where it all comes from 🌱\nStay tuned as these little fluff balls grow! 🐔",
      "created_time": "2026-03-19T19:50:08+0000",
      "permalink_url": "https://www.facebook.com/122162141804942538/posts/122171355008942538",
      "full_picture": "https://scontent-iad3-2.xx.fbcdn.net/v/t39.30808-6/652725877_122171165414942538_477979761408230118_n.jpg?stp=cp1_dst-jpg_s960x960_tt6&_nc_cat=103&ccb=1-7&_nc_sid=7b2446&_nc_ohc=U0utqYYIr2sQ7kNvwEj_IbQ&_nc_oc=Adp13xkF62J3xVZIezN1tJ4wGe3Uq1b3qzCsR6sFq2A597rNwQr0mufDtJZ_LWn7LYs&_nc_zt=23&_nc_ht=scontent-iad3-2.xx&edm=AKK4YLsEAAAA&_nc_gid=1u2gEf9yKyIC2Vp_DoDSKA&_nc_tpa=Q5bMBQGe29bS81MoYKtJq_MAnmu5548pkqsKjyF-yRXd9i8LE70lb1j1fgaZqV5183HJ3FnpSOP_6CVHQQ&oh=00_AfxcZT43BM1AzPS0e8veSbrxK-walC3-WTfTC7bba-bTxA&oe=69C29C78"
    },
    {
      "id": "647110288496461_122171165132942538",
      "message": "🚨 CHICKEN SHARES ARE GOING FAST! 🚨\nWe only have 40 chickens left to claim for the year! 🐔\nDon’t miss your chance to fill your freezer with farm-fresh, locally raised chicken straight from our farm to your table.\n✔️ Raised with care\n✔️ No shortcuts, just quality\n✔️ Stock up for your family\nOnce they’re gone… they’re gone… until next year!\n📩 Message us now to reserve your chicken share!",
      "created_time": "2026-03-18T15:28:19+0000",
      "permalink_url": "https://www.facebook.com/122162141804942538/posts/122171165132942538",
      "full_picture": "https://scontent-iad3-1.xx.fbcdn.net/v/t39.30808-6/654277550_122171165114942538_4676428491363625505_n.jpg?stp=dst-jpg_p720x720_tt6&_nc_cat=110&ccb=1-7&_nc_sid=7b2446&_nc_ohc=wdpTnK6B3eEQ7kNvwFhiHPU&_nc_oc=AdqySawNcFmdka3tHutanV7Go3KkE_IWtJk1uczOqpA35F5pbTyM8740IKtqevjvJR4&_nc_zt=23&_nc_ht=scontent-iad3-1.xx&edm=AKK4YLsEAAAA&_nc_gid=1u2gEf9yKyIC2Vp_DoDSKA&_nc_tpa=Q5bMBQHi8hetRshOpQvQxaQswvpi3Z34xdXIpz2ZXEbg88MDgxv1eMAYeJynD-0B58XCVBI_2kU8IT-zKg&oh=00_AfyvV9O13rySKsipxoUGRP5MmOMguo6p678vu5HXOCai_g&oe=69C28FB9"
    },
    {
      "id": "647110288496461_122170844408942538",
      "message": "As promised, the egg restock! 🥚\n💲3/ dozen \nPick up: 955 Thompson Rd, Dolgeville",
      "created_time": "2026-03-16T21:27:45+0000",
      "permalink_url": "https://www.facebook.com/122162141804942538/posts/122170844408942538",
      "full_picture": "https://scontent-iad3-1.xx.fbcdn.net/v/t39.30808-6/651561071_122170844378942538_4431463425955943113_n.jpg?_nc_cat=110&ccb=1-7&_nc_sid=7b2446&_nc_ohc=4dEoOsfIEjkQ7kNvwEiwIy7&_nc_oc=AdrD4Go0Ia7LhQdau8KFP_C4wpgs5UzM94w3Qjudfq9mzhUzAYyGWNOaojnIVnSnnaw&_nc_zt=23&_nc_ht=scontent-iad3-1.xx&edm=AKK4YLsEAAAA&_nc_gid=1u2gEf9yKyIC2Vp_DoDSKA&_nc_tpa=Q5bMBQGgmV29beA3LZUz_hw7wQfxefo4YZJv4dhsS9bdcddKy2XC1zflsag32FRw8GORtIa6UPAywvLy5A&oh=00_AfxfRdStNdHpmvDZ9OY-Ybi6z-DaXwi08l8kodAmjqhiew&oe=69C2A0E9"
    }
  ]
}