{
  "generated_at": "2026-03-20T17:01:25Z",
  "cutoff_utc": "2026-03-19T17:01:25Z",
  "mode": "fallback_recent",
  "count": 3,
  "posts": [
    {
      "id": "647110288496461_122171355008942538",
      "message": "🐥 The kids have been BUSY this week… 🐥\nWe welcomed 200 new baby chicks to the farm this past weekend!! 😍\nLet’s just say…\nThere’s been a lot of excitement, a little chaos, and a whole lot of peeping going on 🐣😂\nThe kids are already hard at work helping care for them—making sure they’re warm, fed, and getting plenty of love ❤️\nThis is what it’s all about for us…\nRaising food, raising kids, and raising them to know where it all comes from 🌱\nStay tuned as these little fluff balls grow! 🐔",
      "created_time": "2026-03-19T19:50:08+0000",
      "permalink_url": "https://www.facebook.com/122162141804942538/posts/122171355008942538",
      "full_picture": "https://scontent-sea5-1.xx.fbcdn.net/v/t39.30808-6/652725877_122171165414942538_477979761408230118_n.jpg?stp=cp1_dst-jpg_s960x960_tt6&_nc_cat=103&ccb=1-7&_nc_sid=7b2446&_nc_ohc=U0utqYYIr2sQ7kNvwGzBG88&_nc_oc=Adq044vtuMilKWA6hyCuv4Lx-U7Hf2cdXa0TY8jZNqnfcwzBXBzhRnoPzkLbjj647WY&_nc_zt=23&_nc_ht=scontent-sea5-1.xx&edm=AKK4YLsEAAAA&_nc_gid=OUe1qc14d85oCNg17kbfXg&_nc_tpa=Q5bMBQGsAZYHVJks17weHicGMUym6f66441BBR4MBtP5XkY7Jx-spSaqbVM090-O-XecSRIk-Vd_j_2vlw&oh=00_Afz93oa-TuhB8HKRlMH-xq31cDrBuXQ3mvCIqEHQTDn4Jw&oe=69C34538"
    },
    {
      "id": "647110288496461_122171165132942538",
      "message": "🚨 CHICKEN SHARES ARE GOING FAST! 🚨\nWe only have 40 chickens left to claim for the year! 🐔\nDon’t miss your chance to fill your freezer with farm-fresh, locally raised chicken straight from our farm to your table.\n✔️ Raised with care\n✔️ No shortcuts, just quality\n✔️ Stock up for your family\nOnce they’re gone… they’re gone… until next year!\n📩 Message us now to reserve your chicken share!",
      "created_time": "2026-03-18T15:28:19+0000",
      "permalink_url": "https://www.facebook.com/122162141804942538/posts/122171165132942538",
      "full_picture": "https://scontent-sea5-1.xx.fbcdn.net/v/t39.30808-6/654277550_122171165114942538_4676428491363625505_n.jpg?stp=dst-jpg_p720x720_tt6&_nc_cat=110&ccb=1-7&_nc_sid=7b2446&_nc_ohc=wdpTnK6B3eEQ7kNvwHIJmPe&_nc_oc=AdprmQrNYxp8NgJmWv4v1RTpj5DASa6zO39el1V42iq2r4rHyuMTzmlhaCUCwIHyfrk&_nc_zt=23&_nc_ht=scontent-sea5-1.xx&edm=AKK4YLsEAAAA&_nc_gid=OUe1qc14d85oCNg17kbfXg&_nc_tpa=Q5bMBQFp2qWm3h9gIkEWVXkQpMc9nNMOzOq6dfFS2GesNpu_EgjRw3R1shdi-ZBSEVrrJogTY3iqSuiIVg&oh=00_Afxp3P4xJgSdofyxhielvf2mT5wG6HSsDwE7Ixv0qEbMQQ&oe=69C33879"
    },
    {
      "id": "647110288496461_122170844408942538",
      "message": "As promised, the egg restock! 🥚\n💲3/ dozen \nPick up: 955 Thompson Rd, Dolgeville",
      "created_time": "2026-03-16T21:27:45+0000",
      "permalink_url": "https://www.facebook.com/122162141804942538/posts/122170844408942538",
      "full_picture": "https://scontent-sea5-1.xx.fbcdn.net/v/t39.30808-6/651561071_122170844378942538_4431463425955943113_n.jpg?_nc_cat=110&ccb=1-7&_nc_sid=7b2446&_nc_ohc=4dEoOsfIEjkQ7kNvwGuAGDQ&_nc_oc=Adr3oUDUo8R1FO9MelvPxfU9NO7wb7qYkzcqH84YkQXAEb4Dvmqk8QoTCqH-jx7Qg-s&_nc_zt=23&_nc_ht=scontent-sea5-1.xx&edm=AKK4YLsEAAAA&_nc_gid=OUe1qc14d85oCNg17kbfXg&_nc_tpa=Q5bMBQHfLzIXJ2k-3s_jy_OkqFhwsKnD18T5nEHKkMwvkoQbLQb7FFrNbdCNRXpoX9A2RmokW2el2dTgnw&oh=00_AfyLKM7P9yoGBtJHMHlaiC9wx-TFR0_P7ZgKRUStrK1MWQ&oe=69C349A9"
    }
  ]
}