{
  "generated_at": "2026-04-26T16:42:05Z",
  "cutoff_utc": "2026-04-25T16:42:05Z",
  "mode": "fallback_recent",
  "count": 3,
  "posts": [
    {
      "id": "647110288496461_122178781556942538",
      "message": "Don’t forget, EGG DEAL TODAY! \nUntil sold out! 🙂\n\nThank you so much for supporting our local farm 🌾",
      "created_time": "2026-04-26T13:04:26+0000",
      "permalink_url": "https://www.facebook.com/122162141804942538/posts/122178781556942538",
      "full_picture": "https://scontent-iad6-1.xx.fbcdn.net/v/t39.30808-6/683389028_122178781502942538_3812781603431964654_n.jpg?stp=dst-jpg_p720x720_tt6&_nc_cat=106&ccb=1-7&_nc_sid=7b2446&_nc_ohc=WRzXal1lAkwQ7kNvwET8wnv&_nc_oc=AdpIwTCTp04MyeFB1O_d8zlcl0M84nQl0-B5BqJpKl2pLLNmrkyZxfy4M8j-IVvI7_o&_nc_zt=23&_nc_ht=scontent-iad6-1.xx&edm=AKK4YLsEAAAA&_nc_gid=cupcVLKIJQSGn09nsK7MRA&_nc_tpa=Q5bMBQH1M0UwZFRfi-eJ3Lw1edmuvQULikn6VfcLEPoyoSkQUr19fCUSmeTKNxlmNU-hZdf-U1STnpEqyA&oh=00_Af2X3ZZTAb7FToJdN0HRijIOIdgt475H0lQ0Y1FGYufRlw&oe=69F40F79"
    },
    {
      "id": "647110288496461_122178659384942538",
      "message": "🥚 EGGS FOR SALE 🥚\nFresh from our farm to your table!\n🐔 Chicken Eggs – $2/dozen\n🦆 Duck Eggs – $3/half dozen\nConvenient self-serve pickup — stocked in our mini fridge right on the porch!\n📍 955 Thompson Rd, Dolgeville\nStop by anytime and grab yours while they last!",
      "created_time": "2026-04-25T22:59:58+0000",
      "permalink_url": "https://www.facebook.com/122162141804942538/posts/122178659384942538",
      "full_picture": "https://scontent-iad6-1.xx.fbcdn.net/v/t39.30808-6/679420115_122178659354942538_1137197655544660924_n.jpg?stp=dst-jpg_p720x720_tt6&_nc_cat=100&ccb=1-7&_nc_sid=7b2446&_nc_ohc=QWgKThQqdvAQ7kNvwGVCcjo&_nc_oc=AdqWxUr_7YiuqAdow2FbHOm_-jBi-fya3ebNm1JWVhdaG8y6S9j1dEh3PDmLMLKTmCY&_nc_zt=23&_nc_ht=scontent-iad6-1.xx&edm=AKK4YLsEAAAA&_nc_gid=cupcVLKIJQSGn09nsK7MRA&_nc_tpa=Q5bMBQF6To9NgyyU9lPF6ECVoS8SJ6xHRSeBcC_XauqBkcdfB8iUdQIPTN1b8fTa3jZKfOI9LE6EAGHEqg&oh=00_Af2Kz7tOJlrjv6m-AWkBXzS8BnhlbAkORvZ_v9TMyQEH6g&oe=69F41463"
    },
    {
      "id": "647110288496461_122178495818942538",
      "message": "🔥 FIRST SMOKE OF THE YEAR — SIGNAL LOCKED IN 🔥\n\nIf you can smell this through your phone… we did it right.\n\n🍗 BBQ beer can chicken leg quarters coated in our Roswell Family Farm rub\n🥃 Tennessee whiskey marinated leg quarters, finished the same way\n\nThese aren’t small birds.\n\nThese are pasture-raised, Mohawk Valley grown, full-flavor leg quarters—smoked low and heavy.\n\nNo shortcuts. No gimmicks—just out-of-this-world flavor. 🛸\n\nSame chicken we raise for our table—and local restaurants across the valley.\n\n📍 Dolgeville / Salisbury, NY\n🐓 Raised right here on pasture\n\n👇 Be honest…\nhow many of these are you putting down?\n\n#RoswellFamilyFarm #FirstSmoke #AbductedByFlavor #PastureRaised #BBQSeason #SmokedChicken #MohawkValley #UpstateNYFarm #EatLocal #FarmToTable #FoodThatHitsDifferent",
      "created_time": "2026-04-24T22:31:16+0000",
      "permalink_url": "https://www.facebook.com/122162141804942538/posts/122178495818942538",
      "full_picture": "https://scontent-iad6-1.xx.fbcdn.net/v/t39.30808-6/677706265_122178495794942538_87670135599305963_n.jpg?stp=dst-jpg_s1080x2048_tt6&_nc_cat=102&ccb=1-7&_nc_sid=7b2446&_nc_ohc=w02-38dqeOQQ7kNvwGMNPgr&_nc_oc=Adql_xDBkLRy9u9jIlBmOQb5RrCW6wJPzbs25QCIOm_vJ-X02R22yY4KOsGqKpKEt-4&_nc_zt=23&_nc_ht=scontent-iad6-1.xx&edm=AKK4YLsEAAAA&_nc_gid=cupcVLKIJQSGn09nsK7MRA&_nc_tpa=Q5bMBQE-m3_vc6VW9V_TDO8L8sbKH2eILLTEcGWLgQb4OgS66vmLDS-8uYu6EPUxWzmezb681poFhDn0-Q&oh=00_Af2Z16THKSlzO9IW4CikkPp0kyRsXQ9UpgErQgtDLi4nUQ&oe=69F425E0"
    }
  ]
}